sport_activities_features/__init__.py
sport_activities_features/activity_generator.py
sport_activities_features/area_identification.py
sport_activities_features/classes.py
sport_activities_features/data_analysis.py
sport_activities_features/data_extraction.py
sport_activities_features/data_extraction_from_csv.py
sport_activities_features/dead_end_identification.py
sport_activities_features/file_manipulation.py
sport_activities_features/gpx_manipulation.py
sport_activities_features/hill_identification.py
sport_activities_features/interruptions/exercise.py
sport_activities_features/interruptions/exercise_event.py
sport_activities_features/interruptions/interruption_processor.py
sport_activities_features/interruptions/interuption_point.py
sport_activities_features/interruptions/overpass.py
sport_activities_features/interval_identification.py
sport_activities_features/missing_elevation_identification.py
sport_activities_features/overpy_node_manipulation.py
sport_activities_features/plot_data.py
sport_activities_features/tcx_manipulation.py
sport_activities_features/topographic_features.py
sport_activities_features/training_loads.py
sport_activities_features/training_metrics.py
sport_activities_features/weather_identification.py
sport_activities_features/weather_objects/AverageWeather.py
sport_activities_features/weather_objects/Weather.py
sport_activities_features-0.5.2.dist-info/AUTHORS.rst
sport_activities_features-0.5.2.dist-info/LICENSE
sport_activities_features-0.5.2.dist-info/METADATA
sport_activities_features-0.5.2.dist-info/WHEEL
sport_activities_features-0.5.2.dist-info/RECORD
