Metadata-Version: 2.1
Name: sport-activities-features
Version: 0.5.2
Summary: A minimalistic toolbox for extracting features from sport activity files
Home-page: https://github.com/firefly-cpp/sport-activities-features
License: MIT
Keywords: computational intelligence,cycling,data mining,datasets,gpx,optimization,sport activities,tcx
Author: Iztok Fister Jr.
Author-email: iztok@iztok-jr-fister.eu
Requires-Python: >=3.9.0,<4.0.0
Classifier: License :: OSI Approved :: MIT License
Classifier: Programming Language :: Python :: 3
Classifier: Programming Language :: Python :: 3.9
Classifier: Programming Language :: Python :: 3.10
Classifier: Programming Language :: Python :: 3.11
Classifier: Programming Language :: Python :: 3.12
Classifier: Programming Language :: Python :: 3.13
Requires-Dist: geopy (>=2.0.0,<3.0.0)
Requires-Dist: geotiler (>=0.14.5,<0.15.0)
Requires-Dist: gpxpy (==1.4.2)
Requires-Dist: matplotlib (>=3.3.3,<4.0.0)
Requires-Dist: niaaml (>=1.2.0,<2.0.0)
Requires-Dist: numpy
Requires-Dist: overpy (>=0.6,<0.7)
Requires-Dist: pandas
Requires-Dist: tcx2gpx (==0.1.4)
Requires-Dist: tcxreader (>=0.4.11,<0.5.0)
Project-URL: Documentation, https://sport-activities-features.readthedocs.io/en/latest/
Project-URL: Repository, https://github.com/firefly-cpp/sport-activities-features
